kivy_snake_package/__init__.py
kivy_snake_package/main.py
kivy_snake_package/snake.kv
kivy_snake_package-1.1.dist-info/LICENSE
kivy_snake_package-1.1.dist-info/METADATA
kivy_snake_package-1.1.dist-info/WHEEL
kivy_snake_package-1.1.dist-info/entry_points.txt
kivy_snake_package-1.1.dist-info/top_level.txt
kivy_snake_package-1.1.dist-info/RECORD
